ngenicpy/__init__.py
ngenicpy/const.py
ngenicpy/exceptions.py
ngenicpy/ngenic.py
ngenicpy/models/__init__.py
ngenicpy/models/base.py
ngenicpy/models/measurement.py
ngenicpy/models/node.py
ngenicpy/models/node_status.py
ngenicpy/models/room.py
ngenicpy/models/setpoint_schedule.py
ngenicpy/models/tune.py
ngenicpy-0.5.2.dist-info/METADATA
ngenicpy-0.5.2.dist-info/WHEEL
ngenicpy-0.5.2.dist-info/licenses/LICENSE
ngenicpy-0.5.2.dist-info/RECORD
