Metadata-Version: 2.4
Name: ngenicpy
Version: 0.5.2
Summary: Python package for simple access to Ngenic Tune API.
Project-URL: Homepage, https://github.com/dotnetdummy/ngenicpy
Project-URL: Documentation, https://github.com/dotnetdummy/ngenicpy
Project-URL: Repository, https://github.com/dotnetdummy/ngenicpy.git
Project-URL: Issues, https://github.com/dotnetdummy/ngenicpy/issues
Project-URL: Changelog, https://github.com/dotnetdummy/ngenicpy/releases
Author-email: Carl Ripa <cj.ripa@gmail.com>, Simon Falkman <sfalkman@gmail.com>
Maintainer-email: Carl Ripa <cj.ripa@gmail.com>
License-Expression: MIT
License-File: LICENSE
Keywords: api,hass,integration,ngenic,sdk
Classifier: Operating System :: OS Independent
Classifier: Programming Language :: Python :: 3
Requires-Python: >=3.12
Requires-Dist: httpx>=0.28.1
